instagraper/__init__.py
instagraper/__main__.py
instagraper/cleaner.py
instagraper/cli.py
instagraper/exceptions.py
instagraper/geojson.py
instagraper/map.py
instagraper/models.py
instagraper/scraper.py
instagraper/template.py
instagraper/templates/map.html
instagraper/utils.py
instagraper-0.1.6.dist-info/LICENSE
instagraper-0.1.6.dist-info/METADATA
instagraper-0.1.6.dist-info/WHEEL
instagraper-0.1.6.dist-info/entry_points.txt
instagraper-0.1.6.dist-info/RECORD
