Metadata-Version: 2.1
Name: instagraper
Version: 0.1.6
Summary: 
Author: Francisco Macedo
Author-email: franciscovcbm@gmail.com
Requires-Python: >=3.10,<4.0
Classifier: Programming Language :: Python :: 3
Classifier: Programming Language :: Python :: 3.10
Classifier: Programming Language :: Python :: 3.11
Classifier: Programming Language :: Python :: 3.12
Provides-Extra: cli
Requires-Dist: python-decouple (>=3.8,<4.0)
Requires-Dist: requests (>=2.31.0,<3.0.0)
Requires-Dist: rich (>=13.7.0,<14.0.0)
Requires-Dist: typer[all] (>=0.9.0,<0.10.0) ; extra == "cli"
